anthemav_serial/__init__.py
anthemav_serial/config.py
anthemav_serial/const.py
anthemav_serial/protocol_async.py
anthemav_serial/protocol_sync.py
anthemav_serial/protocols/anthem_rs232_gen1.yaml
anthemav_serial/protocols/anthem_rs232_gen2.yaml
anthemav_serial/series/avm50.yaml
anthemav_serial/series/avm60.yaml
anthemav_serial/series/d1.yaml
anthemav_serial/series/d2.yaml
anthemav_serial/series/d2v.yaml
anthemav_serial/series/mrx2.yaml
anthemav_serial-0.4.1.dist-info/LICENSE.md
anthemav_serial-0.4.1.dist-info/METADATA
anthemav_serial-0.4.1.dist-info/WHEEL
anthemav_serial-0.4.1.dist-info/top_level.txt
anthemav_serial-0.4.1.dist-info/zip-safe
anthemav_serial-0.4.1.dist-info/RECORD
